{"_ts":[1514805268],"_r":{"breakdown":{"html":{"bytes":[7442],"requests":[4]},"js":{"bytes":[188033],"requests":[11]},"css":{"bytes":[142039],"requests":[15]},"image":{"bytes":[622827],"requests":[17]},"flash":{"bytes":[0],"requests":[0]},"font":{"bytes":[94241],"requests":[7]},"video":{"bytes":[0],"requests":[0]},"other":{"bytes":[0],"requests":[0]}},"date":[1514805268],"domElements":[319],"domInteractive":[1190],"firstPaint":[1150],"fullyLoaded":[5534],"id":["180101_HY_5e52d2f019fe22437c34f10a5affeb84"],"loadTime":[2970],"render":[1290],"SpeedIndex":[1710],"TTFB":[435],"videoFrames":[[{"_i":"frame_0000.jpg","_t":0,"_vc":0},{"_i":"frame_0013.jpg","_t":1300,"_vc":14},{"_i":"frame_0016.jpg","_t":1600,"_vc":32},{"_i":"frame_0017.jpg","_t":1700,"_vc":79},{"_i":"frame_0020.jpg","_t":2000,"_vc":99},{"_i":"frame_0041.jpg","_t":4100,"_vc":100},{"_i":"frame_0043.jpg","_t":4300,"_vc":100},{"_i":"frame_0044.jpg","_t":4400,"_vc":100},{"_i":"frame_0054.jpg","_t":5400,"_vc":100},{"_i":"frame_0056.jpg","_t":5600,"_vc":100},{"_i":"frame_0058.jpg","_t":5800,"_vc":100}]],"visualComplete":[4100],"lighthouse":[null],"pagespeed":[72]}}