{"_ts":[1504265092,1504300918,1504308882,1504342858,1504352974],"_r":{"breakdown":{"html":{"bytes":[9690,9332,9331,9697,9281],"requests":[4,4,4,4,4]},"js":{"bytes":[76573,76573,76573,76573,76573],"requests":[11,11,11,11,11]},"css":{"bytes":[78611,78611,78611,78611,78611],"requests":[14,14,14,14,14]},"image":{"bytes":[751293,751293,751293,751293,751293],"requests":[25,25,25,25,25]},"flash":{"bytes":[0,0,0,0,0],"requests":[0,0,0,0,0]},"font":{"bytes":[55544,55548,55548,55548,55548],"requests":[4,4,4,4,4]},"other":{"bytes":[0,0,0,0,0],"requests":[0,0,0,0,0]}},"date":[1504265092,1504300918,1504308882,1504342858,1504352974],"domElements":[726,726,726,726,726],"domInteractive":[1507,816,831,973,852],"firstPaint":[1403,684,722,856,746],"fullyLoaded":[3568,2765,2726,2864,2780],"id":["170901_8J_f77a12643310194de2a9361167f7b586","170901_B4_694f38b70c01285f45894520fd406efe","170901_J2_46cc5e11e6e7588f5860929c1e0ae916","170902_0T_34857312fdf6825b0a0a295ecd140522","170902_TH_4e92ac34fb7e1390e3a4fe5e74d2ce66"],"loadTime":[3492,2692,2648,2787,2704],"render":[1501,799,813,992,814],"SpeedIndex":[2761,2059,1464,1859,1442],"TTFB":[554,253,291,412,294],"videoFrames":[[{"_i":"frame_0000.jpg","_t":0,"_vc":0},{"_i":"frame_0015.jpg","_t":1500,"_vc":12},{"_i":"frame_0017.jpg","_t":1700,"_vc":14},{"_i":"frame_0019.jpg","_t":1900,"_vc":17},{"_i":"frame_0030.jpg","_t":3000,"_vc":100},{"_i":"frame_0036.jpg","_t":3600,"_vc":100}],[{"_i":"frame_0000.jpg","_t":0,"_vc":0},{"_i":"frame_0008.jpg","_t":800,"_vc":12},{"_i":"frame_0010.jpg","_t":1000,"_vc":15},{"_i":"frame_0012.jpg","_t":1200,"_vc":17},{"_i":"frame_0023.jpg","_t":2300,"_vc":100},{"_i":"frame_0029.jpg","_t":2900,"_vc":100}],[{"_i":"frame_0000.jpg","_t":0,"_vc":0},{"_i":"frame_0008.jpg","_t":800,"_vc":12},{"_i":"frame_0010.jpg","_t":1000,"_vc":39},{"_i":"frame_0012.jpg","_t":1200,"_vc":39},{"_i":"frame_0018.jpg","_t":1800,"_vc":100},{"_i":"frame_0027.jpg","_t":2700,"_vc":100}],[{"_i":"frame_0000.jpg","_t":0,"_vc":0},{"_i":"frame_0010.jpg","_t":1000,"_vc":12},{"_i":"frame_0012.jpg","_t":1200,"_vc":17},{"_i":"frame_0013.jpg","_t":1300,"_vc":40},{"_i":"frame_0023.jpg","_t":2300,"_vc":100},{"_i":"frame_0029.jpg","_t":2900,"_vc":100}],[{"_i":"frame_0000.jpg","_t":0,"_vc":0},{"_i":"frame_0008.jpg","_t":800,"_vc":12},{"_i":"frame_0010.jpg","_t":1000,"_vc":17},{"_i":"frame_0012.jpg","_t":1200,"_vc":40},{"_i":"frame_0017.jpg","_t":1700,"_vc":100},{"_i":"frame_0028.jpg","_t":2800,"_vc":100}]],"visualComplete":[3000,2300,1800,2300,1700],"lighthouse":[null,null,null,null,null],"pagespeed":[76,76,76,76,76]}}